cloud_fs/__init__.py
cloud_fs/cloud_fs.py
cloud_fs/filesystems.py
cloud_fs/version.py
NREL_cloud_fs-0.0.8.dist-info/LICENSE
NREL_cloud_fs-0.0.8.dist-info/METADATA
NREL_cloud_fs-0.0.8.dist-info/WHEEL
NREL_cloud_fs-0.0.8.dist-info/top_level.txt
NREL_cloud_fs-0.0.8.dist-info/RECORD
