Metadata-Version: 2.1
Name: NREL-cloud-fs
Version: 0.0.8
Summary: `cloud-fs` is a generalized file-system handler that will dynamically determine if files are local or on the cloud (currently AWS) and perform basic file-systm operations.
Home-page: https://nrel.github.io/cloud_fs/
Author: Michael Rossol
Author-email: michael.rossol@nrel.gov
License: BSD 3-Clause
Keywords: cloud_fs
Platform: UNKNOWN
Classifier: Development Status :: 4 - Beta
Classifier: Intended Audience :: Science/Research
Classifier: License :: OSI Approved :: BSD License
Classifier: Natural Language :: English
Classifier: Programming Language :: Python :: 3.7
Classifier: Programming Language :: Python :: 3.8
Classifier: Programming Language :: Python :: 3.9
Requires-Python: >=3.7
License-File: LICENSE
Requires-Dist: s3fs (>=2021.5.0)
Provides-Extra: dev
Requires-Dist: pytest (>=5.2) ; extra == 'dev'
Requires-Dist: h5py (!=3.0.0,>=2.10.0) ; extra == 'dev'
Requires-Dist: flake8 ; extra == 'dev'
Requires-Dist: pre-commit ; extra == 'dev'
Requires-Dist: pylint ; extra == 'dev'
Provides-Extra: test
Requires-Dist: pytest (>=5.2) ; extra == 'test'
Requires-Dist: h5py (!=3.0.0,>=2.10.0) ; extra == 'test'
